README.txt
buildout.cfg
setup.py
src/iwm/__init__.py
src/iwm.recipe.blobstorage.egg-info/PKG-INFO
src/iwm.recipe.blobstorage.egg-info/SOURCES.txt
src/iwm.recipe.blobstorage.egg-info/dependency_links.txt
src/iwm.recipe.blobstorage.egg-info/entry_points.txt
src/iwm.recipe.blobstorage.egg-info/requires.txt
src/iwm.recipe.blobstorage.egg-info/top_level.txt
src/iwm/recipe/__init__.py
src/iwm/recipe/blobstorage/__init__.py
src/iwm/recipe/blobstorage/tests.py
