Metadata-Version: 1.0
Name: iwm.recipe.blobstorage
Version: 0.0.2
Summary: ZC Buildout recipe for defining a blob-storage
Home-page: http://svn.kmrc.de/projects/devel/iwm.recipe.blobstorage
Author: Torsten Kurbad
Author-email: t.kurbad@iwm-kmrc.de
License: GPL
Keywords: zope3 bebop blobstorage
Platform: UNKNOWN
